LICENSE
MANIFEST.in
README.rst
requirements.txt
setup.cfg
setup.py
gdsctools/__init__.py
gdsctools/annotate_genes.py
gdsctools/anova.py
gdsctools/anova_report.py
gdsctools/anova_results.py
gdsctools/boxplots.py
gdsctools/boxswarm.py
gdsctools/cosmictools.py
gdsctools/datasets.py
gdsctools/default_sets.py
gdsctools/drugs.py
gdsctools/errors.py
gdsctools/fetch_drug_data.py
gdsctools/fetch_gdsc_data.py
gdsctools/filter.py
gdsctools/gdsc.py
gdsctools/gdsc1000.py
gdsctools/logistics.py
gdsctools/models.py
gdsctools/omnibem.py
gdsctools/qvalue.py
gdsctools/readers.py
gdsctools/regression.py
gdsctools/regression_report.py
gdsctools/report.py
gdsctools/settings.py
gdsctools/stats.py
gdsctools/tissues.py
gdsctools/tools.py
gdsctools/volcano.py
gdsctools.egg-info/PKG-INFO
gdsctools.egg-info/SOURCES.txt
gdsctools.egg-info/dependency_links.txt
gdsctools.egg-info/entry_points.txt
gdsctools.egg-info/not-zip-safe
gdsctools.egg-info/requires.txt
gdsctools.egg-info/top_level.txt
gdsctools/data/DRUG_DECODE.csv
gdsctools/data/GF_BRCA_v17.csv.gz
gdsctools/data/GF_BRCA_v17.tsv
gdsctools/data/IC50_10drugs.tsv
gdsctools/data/IC50_v17.csv.gz
gdsctools/data/IC50_v5.csv.gz
gdsctools/data/__init__.py
gdsctools/data/cancer_cell_lines.csv
gdsctools/data/cosmic_builder_test.txt
gdsctools/data/cosmic_info.csv.gz
gdsctools/data/genomic_features.tsv.gz
gdsctools/data/genomic_features_v17.csv.gz
gdsctools/data/genomic_features_v5.csv.gz
gdsctools/data/test_ANOVA_input_v17_skcm.txt
gdsctools/data/test_IC50.csv
gdsctools/data/test_IC50_header1.csv
gdsctools/data/test_IC50_header2.csv
gdsctools/data/test_IC50_header3.csv
gdsctools/data/test_IC50_tabs.csv
gdsctools/data/test_drug_decode.csv
gdsctools/data/test_drug_decode.tsv
gdsctools/data/test_drug_decode2.csv
gdsctools/data/test_drug_decode_comp.csv
gdsctools/data/test_genomic_features.csv
gdsctools/data/test_genomic_features_bare.csv
gdsctools/data/test_ic50_11_50.csv
gdsctools/data/test_omnibem_filtered.csv
gdsctools/data/test_omnibem_genes.txt
gdsctools/data/test_omnibem_genomic_alterations.csv.gz
gdsctools/data/test_v18_clustering.tsv
gdsctools/data/css/__init__.py
gdsctools/data/css/canvasXpress.css
gdsctools/data/css/gdsc.css
gdsctools/data/css/global.css
