Metadata-Version: 1.1
Name: gdsctools
Version: 1.0.1
Summary: Set of tools and pipelines to analyse GDSC data (cancerrxgene.org)
Home-page: ['http://pypi.python.org/pypi/gdsctools']
Author: Thomas Cokelaer
Author-email: cokelaer@gmail.com
License: BSD
Download-URL: ['http://pypi.python.org/pypi/gdsctools']
Keywords: gdsc,drug response,anova,genomic features
Platform: Linux
Platform: Unix
Platform: MacOsX
Platform: Windows
Classifier: Development Status :: 1 - Planning
Classifier: Intended Audience :: Developers
Classifier: Intended Audience :: Science/Research
Classifier: License :: OSI Approved :: BSD License
Classifier: Operating System :: OS Independent
Classifier: Programming Language :: Python :: 2.7
Classifier: Programming Language :: Python :: 3.5
Classifier: Programming Language :: Python :: 3.6
Classifier: Topic :: Software Development :: Libraries :: Python Modules
Classifier: Topic :: Scientific/Engineering :: Bio-Informatics
Classifier: Topic :: Scientific/Engineering :: Information Analysis
Classifier: Topic :: Scientific/Engineering :: Mathematics
Classifier: Topic :: Scientific/Engineering :: Physics
